instaup/__init__.py
instaup/instaup.py
instaup-2020.6.29.dist-info/LICENSE
instaup-2020.6.29.dist-info/METADATA
instaup-2020.6.29.dist-info/WHEEL
instaup-2020.6.29.dist-info/entry_points.txt
instaup-2020.6.29.dist-info/top_level.txt
instaup-2020.6.29.dist-info/RECORD
