Metadata-Version: 2.1
Name: instaup
Version: 2020.6.29
Summary: An auto downloader and uploader for Instagram profiles.
Home-page: https://github.com/Coloradohusky/InstaUp
Author: Coloradohusky
License: UNKNOWN
Platform: UNKNOWN
Requires-Python: >=3.5, <4
Requires-Dist: internetarchive (>=1.9.3)
Requires-Dist: instaloader (>=4.4.3)
